jadoc/__init__.py
jadoc/conj.py
jadoc/doc.py
jadoc/errors.py
jadoc/mecab/__init__.py
jadoc/mecab/config.py
jadoc/mecab/tokenizer.py
jadoc/utils.py
jadoc/word/__init__.py
jadoc/word/cform.py
jadoc/word/ctype.py
jadoc/word/pos.py
jadoc/word/word.py
jadoc-0.2.5.dist-info/LICENSE
jadoc-0.2.5.dist-info/WHEEL
jadoc-0.2.5.dist-info/METADATA
jadoc-0.2.5.dist-info/RECORD
