Metadata-Version: 2.1
Name: jadoc
Version: 0.2.5
Summary: Tokenizes Japanese documents to enable CRUD operations.
Home-page: https://github.com/poyo46/jadoc
License: Apache-2.0
Keywords: japanese,conjugate,inflect,tokenize,crud,nlp,mecab
Author: poyo46
Author-email: poyo4rock@gmail.com
Requires-Python: >=3.6,<4.0
Classifier: Development Status :: 3 - Alpha
Classifier: Intended Audience :: Developers
Classifier: License :: OSI Approved :: Apache Software License
Classifier: Natural Language :: Japanese
Classifier: Operating System :: MacOS :: MacOS X
Classifier: Operating System :: POSIX :: Linux
Classifier: Programming Language :: Python :: 3
Classifier: Programming Language :: Python :: 3.6
Classifier: Programming Language :: Python :: 3.7
Classifier: Programming Language :: Python :: 3.8
Classifier: Programming Language :: Python :: 3.9
Classifier: Topic :: Text Processing :: Linguistic
Requires-Dist: mecab-python3 (>=1.0.3,<2.0.0)
Project-URL: Repository, https://github.com/poyo46/jadoc
